setup.py
ABC/__init__.py
CCC.py.egg-info/PKG-INFO
CCC.py.egg-info/SOURCES.txt
CCC.py.egg-info/dependency_links.txt
CCC.py.egg-info/top_level.txt
QQX/__init__.py