Metadata-Version: 2.1
Name: CCC.py
Version: 109
Summary: [我是一隻小貓]
Home-page: UNKNOWN
Author: moon-start
Author-email: moon-start@gmail.com
License: LGPL
Platform: UNKNOWN
